cadenza/__init__.py
cadenza/enhance.py
cadenza/evaluate.py
cadenza/merge_batches_results.py
cadenza/test.py
xumx_slicq_v2/__init__.py
xumx_slicq_v2/__main__.py
xumx_slicq_v2/data.py
xumx_slicq_v2/demixui.py
xumx_slicq_v2/evaluation.py
xumx_slicq_v2/export.py
xumx_slicq_v2/inference.py
xumx_slicq_v2/kivy.py
xumx_slicq_v2/loss.py
xumx_slicq_v2/model.py
xumx_slicq_v2/optuna.py
xumx_slicq_v2/phase.py
xumx_slicq_v2/separator.py
xumx_slicq_v2/slicqfinder.py
xumx_slicq_v2/training.py
xumx_slicq_v2/transforms.py
xumx_slicq_v2/visualization.py
xumx_slicq_v2/norbert/__init__.py
xumx_slicq_v2/norbert/contrib.py
xumx_slicq_v2/norbert/utils.py
xumx_slicq_v2/nsgt/__init__.py
xumx_slicq_v2/nsgt/fscale.py
xumx_slicq_v2/nsgt/nsgfwin_sl.py
xumx_slicq_v2/nsgt/nsgtf.py
xumx_slicq_v2/nsgt/nsigtf.py
xumx_slicq_v2/nsgt/reblock.py
xumx_slicq_v2/nsgt/slicing.py
xumx_slicq_v2/nsgt/slicq.py
xumx_slicq_v2/nsgt/unslicing.py
xumx_slicq_v2/nsgt/util.py
xumx_slicq_v2/tests/__init__.py
xumx_slicq_v2/tests/test_phase.py
xumx_slicq_v2-1.0.0a2.dist-info/LICENSE
xumx_slicq_v2-1.0.0a2.dist-info/METADATA
xumx_slicq_v2-1.0.0a2.dist-info/WHEEL
xumx_slicq_v2-1.0.0a2.dist-info/top_level.txt
xumx_slicq_v2-1.0.0a2.dist-info/RECORD
