Metadata-Version: 2.1
Name: xumx-slicq-v2
Version: 1.0.0a2
Summary: V2 of my original sliCQT adaptation of Open-Unmix
Home-page: https://github.com/sevagh/xumx-sliCQ-V2
Author: Sevag Hanssian
Author-email: sevagh@pm.me
License: MIT
Classifier: Development Status :: 4 - Beta
Classifier: Programming Language :: Python :: 3.8
Classifier: License :: OSI Approved :: MIT License
Classifier: Operating System :: OS Independent
Requires-Python: >=3.8
License-File: LICENSE
Requires-Dist: torch (>=2.0.0)
Requires-Dist: torchaudio (>=2.0.0)
Requires-Dist: numpy
Requires-Dist: tqdm
Requires-Dist: requests
Requires-Dist: scipy
Provides-Extra: demixui
Requires-Dist: kivy ; extra == 'demixui'
Requires-Dist: kivymd ; extra == 'demixui'
Requires-Dist: kivy-garden ; extra == 'demixui'
Requires-Dist: onnxruntime ; extra == 'demixui'
Requires-Dist: onnx ; extra == 'demixui'
Requires-Dist: matplotlib ; extra == 'demixui'
Provides-Extra: devel
Requires-Dist: tensorboard ; extra == 'devel'
Requires-Dist: torchinfo ; extra == 'devel'
Requires-Dist: scikit-learn ; extra == 'devel'
Requires-Dist: auraloss ; extra == 'devel'
Requires-Dist: optuna ; extra == 'devel'
Requires-Dist: optuna-dashboard ; extra == 'devel'
Requires-Dist: matplotlib ; extra == 'devel'
Requires-Dist: musdb ; extra == 'devel'
Requires-Dist: museval ; extra == 'devel'
Requires-Dist: pytest ; extra == 'devel'
Provides-Extra: musdb
Requires-Dist: musdb ; extra == 'musdb'
Requires-Dist: museval ; extra == 'musdb'
Provides-Extra: onnxruntime-cpu
Requires-Dist: onnx ; extra == 'onnxruntime-cpu'
Requires-Dist: onnxruntime ; extra == 'onnxruntime-cpu'
Provides-Extra: onnxruntime-cuda
Requires-Dist: onnx ; extra == 'onnxruntime-cuda'
Requires-Dist: onnxruntime-gpu ; extra == 'onnxruntime-cuda'
Requires-Dist: tensorrt ; extra == 'onnxruntime-cuda'
Provides-Extra: tests
Requires-Dist: pytest ; extra == 'tests'
